jconsole
jruntime.cpython-38-x86_64-linux-gnu.so
libj.so
libomp.so
jruntime-0.2.0.post1.dist-info/METADATA
jruntime-0.2.0.post1.dist-info/WHEEL
jruntime-0.2.0.post1.dist-info/top_level.txt
jruntime-0.2.0.post1.dist-info/RECORD
